wirl_lang/__init__.py
wirl_lang/wirl.bnf
wirl_lang/wirl_parser.py
wirl_lang-0.1.0.dist-info/METADATA
wirl_lang-0.1.0.dist-info/WHEEL
wirl_lang-0.1.0.dist-info/RECORD
