Metadata-Version: 2.4
Name: wirl-lang
Version: 0.1.0
Summary: WIRL workflow DSL grammar and parser
Project-URL: Repository, https://github.com/wirl/packages/wirl-lang
Author: Artem Goncharov
License: MIT
Requires-Python: >=3.10
Requires-Dist: lark>=1.1.9
Provides-Extra: dev
Requires-Dist: ruff>=0.5.0; extra == 'dev'
